ticketsdk/__init__.py
ticketsdk/client.py
ticketsdk/constants.py
ticketsdk/validators.py
ticketsdk/seller/__init__.py
ticketsdk-2.3.4.dist-info/METADATA
ticketsdk-2.3.4.dist-info/WHEEL
ticketsdk-2.3.4.dist-info/dependency_links.txt
ticketsdk-2.3.4.dist-info/top_level.txt
ticketsdk-2.3.4.dist-info/RECORD
